AUTHORS.rst
CONTRIBUTING.rst
HISTORY.rst
LICENSE
MANIFEST.in
README.rst
requirements.txt
setup.py
roomyjob/__init__.py
roomyjob/roomyjob.py
roomyjob.egg-info/PKG-INFO
roomyjob.egg-info/SOURCES.txt
roomyjob.egg-info/dependency_links.txt
roomyjob.egg-info/entry_points.txt
roomyjob.egg-info/not-zip-safe
roomyjob.egg-info/requires.txt
roomyjob.egg-info/top_level.txt