Metadata-Version: 1.1
Name: roomyjob
Version: 0.0.8
Summary: Jobs package for roomy
Home-page: https://github.com/bwghughes/roomyjob
Author: Ben Hughes
Author-email: bwghughes@gmail.com
License: BSD
Keywords: roomyjob
Platform: UNKNOWN
Classifier: Development Status :: 2 - Pre-Alpha
Classifier: Intended Audience :: Developers
Classifier: License :: OSI Approved :: BSD License
Classifier: Natural Language :: English
Classifier: Programming Language :: Python :: 2
Classifier: Programming Language :: Python :: 2.6
Classifier: Programming Language :: Python :: 2.7
Classifier: Programming Language :: Python :: 3
Classifier: Programming Language :: Python :: 3.3
